Metadata-Version: 2.1
Name: libGetAvatarGitHub
Version: 0.2
Summary: Módulo criado para exemplificar construção de projetos Python no curso PyTools
Home-page: https://github.com/WschmidtS/libpythonpro
Author: Walter Schmidt
Author-email: suporte@python.pro.br
License: GNU AFFERO GENERAL PUBLIC LICENSE
Platform: UNKNOWN
Classifier: Development Status :: 2 - Pre-Alpha
Classifier: Environment :: Console
Classifier: Intended Audience :: Developers
Classifier: License :: OSI Approved :: GNU Affero General Public License v3 or later (AGPLv3+)
Classifier: Operating System :: OS Independent
Classifier: Programming Language :: Python
Classifier: Programming Language :: Python :: 3.8
Classifier: Framework :: Pytest
